odoo/addons/project_task_stage_allow_timesheet/README.rst
odoo/addons/project_task_stage_allow_timesheet/__init__.py
odoo/addons/project_task_stage_allow_timesheet/__manifest__.py
odoo/addons/project_task_stage_allow_timesheet/i18n/de.po
odoo/addons/project_task_stage_allow_timesheet/i18n/es.po
odoo/addons/project_task_stage_allow_timesheet/i18n/fr.po
odoo/addons/project_task_stage_allow_timesheet/i18n/it.po
odoo/addons/project_task_stage_allow_timesheet/i18n/project_task_stage_allow_timesheet.pot
odoo/addons/project_task_stage_allow_timesheet/models/__init__.py
odoo/addons/project_task_stage_allow_timesheet/models/account_analytic_line.py
odoo/addons/project_task_stage_allow_timesheet/models/project_task_type.py
odoo/addons/project_task_stage_allow_timesheet/readme/CONTRIBUTORS.rst
odoo/addons/project_task_stage_allow_timesheet/readme/DESCRIPTION.rst
odoo/addons/project_task_stage_allow_timesheet/readme/USAGE.rst
odoo/addons/project_task_stage_allow_timesheet/static/description/icon.png
odoo/addons/project_task_stage_allow_timesheet/static/description/index.html
odoo/addons/project_task_stage_allow_timesheet/tests/__init__.py
odoo/addons/project_task_stage_allow_timesheet/tests/test_project_task_stage_allow_timesheet.py
odoo/addons/project_task_stage_allow_timesheet/views/account_analytic_line.xml
odoo/addons/project_task_stage_allow_timesheet/views/project_task_type.xml
odoo_addon_project_task_stage_allow_timesheet-16.0.1.0.0.3.dist-info/METADATA
odoo_addon_project_task_stage_allow_timesheet-16.0.1.0.0.3.dist-info/WHEEL
odoo_addon_project_task_stage_allow_timesheet-16.0.1.0.0.3.dist-info/top_level.txt
odoo_addon_project_task_stage_allow_timesheet-16.0.1.0.0.3.dist-info/RECORD
