Metadata-Version: 2.1
Name: odoo-addon-project-task-stage-allow-timesheet
Version: 16.0.1.0.0.3
Summary: Allows to tell that a task stage is opened for timesheets.
Home-page: https://github.com/OCA/timesheet
Author: Odoo Community Association (OCA), ACSONE SA/NV
Author-email: support@odoo-community.org
License: AGPL-3
Platform: UNKNOWN
Classifier: Programming Language :: Python
Classifier: Framework :: Odoo
Classifier: Framework :: Odoo :: 16.0
Classifier: License :: OSI Approved :: GNU Affero General Public License v3
Requires-Python: >=3.10
Requires-Dist: odoo <16.1dev,>=16.0a
